snipster/__init__.py
snipster/__main__.py
snipster/cli.py
snipster/exceptions.py
snipster/models.py
snipster/repo.py
snipster_kp-0.1.0.dist-info/METADATA
snipster_kp-0.1.0.dist-info/WHEEL
snipster_kp-0.1.0.dist-info/entry_points.txt
snipster_kp-0.1.0.dist-info/RECORD
