Metadata-Version: 2.4
Name: snipster-kp
Version: 0.1.0
Summary: A tool to store and manage code snippets.
Author-email: Kishan Patel <kishanpatel789@gmail.com>
Requires-Python: >=3.13
Requires-Dist: fastapi[all]>=0.115.12
Requires-Dist: flask-wtf>=1.2.2
Requires-Dist: flask>=3.1.1
Requires-Dist: httpx>=0.28.1
Requires-Dist: python-decouple>=3.8
Requires-Dist: sqlmodel>=0.0.24
Requires-Dist: typer>=0.16.0
